setup.py
teamSpeakTelegram/__init__.py
teamSpeakTelegram/__main__.py
teamSpeakTelegram/teamspeak.py
teamSpeakTelegram/utils.py
teamSpeakTelegram.egg-info/PKG-INFO
teamSpeakTelegram.egg-info/SOURCES.txt
teamSpeakTelegram.egg-info/dependency_links.txt
teamSpeakTelegram.egg-info/not-zip-safe
teamSpeakTelegram.egg-info/requires.txt
teamSpeakTelegram.egg-info/top_level.txt
teamSpeakTelegram/locale/es/LC_MESSAGES/teamspeak.mo
teamSpeakTelegram/locale/es/LC_MESSAGES/teamspeak.po