Metadata-Version: 1.0
Name: teamSpeakTelegram
Version: 0.5.0
Summary: A telegram bot that tells you who is connected to the teamspeak server to know when your friends are online.
Home-page: https://github.com/jossalgon/teamSpeakTelegram
Author: Jose Luis Salazar Gonzalez
Author-email: joseluis25sg@gmail.com
License: UNKNOWN
Platform: UNKNOWN
